regex_enumerator/__init__.py
regex_enumerator/regex_enumerator.py
regex_enumerator/regex_parser.py
regex_enumerator/regex_tree.py
regex_enumerator-1.0.0.dist-info/LICENSE
regex_enumerator-1.0.0.dist-info/METADATA
regex_enumerator-1.0.0.dist-info/WHEEL
regex_enumerator-1.0.0.dist-info/top_level.txt
regex_enumerator-1.0.0.dist-info/RECORD
