Metadata-Version: 2.1
Name: regex_enumerator
Version: 1.0.0
Summary: Enumerate all strings that match a given regex
Home-page: https://github.com/Buba98/regex_enumerator
Author: Vincenzo Greco
Author-email: grecovincenzo98@gmail.com
License: MIT
Keywords: regex,regex enumerator,regular expression,enumerator,string generation,exhaustive matching,exhaustive search,regex testing,regex tools,string enumeration,data generation
Classifier: Programming Language :: Python :: 3.10
Classifier: Operating System :: OS Independent
Classifier: License :: OSI Approved :: MIT License
Requires-Python: >=3.10
License-File: LICENSE
Provides-Extra: dev
Requires-Dist: pytest; extra == "dev"
Requires-Dist: pytest-cov; extra == "dev"
